spty.py
simple_pty-1.0.0.dist-info/LICENSE
simple_pty-1.0.0.dist-info/WHEEL
simple_pty-1.0.0.dist-info/METADATA
simple_pty-1.0.0.dist-info/RECORD
